data_sets/__init__.py
sample_code/__init__.py
src/__init__.py
src/__ivnn.py
src/__ivnn_collection.py
src/__nset.py
src/__svnn.py
src/__svnn_collection.py
src/ahp.py
src/ahp_helper.py
src/ahp_topsis.py
src/svtnn.py
test/__init__.py
test/__test_basic_operations.py
test/__test_svnn_and_svnn_collection.py
test/__test_svnn_and_svnn_collection_II.py
neutrosophic-0.0.5.dist-info/LICENSE
neutrosophic-0.0.5.dist-info/METADATA
neutrosophic-0.0.5.dist-info/WHEEL
neutrosophic-0.0.5.dist-info/top_level.txt
neutrosophic-0.0.5.dist-info/RECORD
