Metadata-Version: 2.1
Name: neutrosophic
Version: 0.0.5
Summary: Novel Open Source Python based Neutrosophic Package
Home-page: UNKNOWN
Author: Haitham Abdel Monem El-Ghareeb
Author-email: helghareeb@gmail.com
License: MIT
Platform: UNKNOWN
Classifier: Programming Language :: Python :: 3.6
Requires-Python: >=3.6.0
Requires-Dist: numpy (==1.16.4)
Requires-Dist: pandas (==0.24)
Requires-Dist: matplotlib
